rotki_sqlite-2025.8.1.dist-info/licenses/LICENSE
rsqlite/__init__.py
rsqlite/__init__.pyi
rsqlite/_sqlite3.cp311-win32.pyd
rsqlite/dbapi2.py
rotki_sqlite-2025.8.1.dist-info/METADATA
rotki_sqlite-2025.8.1.dist-info/WHEEL
rotki_sqlite-2025.8.1.dist-info/top_level.txt
rotki_sqlite-2025.8.1.dist-info/RECORD
