Metadata-Version: 2.4
Name: rotki-sqlite
Version: 2025.8.1
Summary: DB-API 2.0 interface for Sqlite 3.x
Author-email: Rotki Solutions GmbH <info@rotki.com>
License: zlib/libpng
Project-URL: Homepage, https://github.com/rotki/rotki-sqlite
Classifier: Development Status :: 4 - Beta
Classifier: Intended Audience :: Developers
Classifier: License :: OSI Approved :: zlib/libpng License
Classifier: Operating System :: MacOS :: MacOS X
Classifier: Operating System :: Microsoft :: Windows
Classifier: Operating System :: POSIX
Classifier: Programming Language :: C
Classifier: Programming Language :: Python
Classifier: Topic :: Database :: Database Engines/Servers
Classifier: Topic :: Software Development :: Libraries :: Python Modules
Requires-Python: ==3.11.*
License-File: LICENSE
Dynamic: license-file
